{
  "project_info": {
    "project_number": "278308056726",
    "project_id": "react-d6253",
    "storage_bucket": "react-d6253.appspot.com"
  },
  "client": [
    {
      "client_info": {
        "mobilesdk_app_id": "1:278308056726:android:de6121fb0d2258e7695cb7",
        "android_client_info": {
          "package_name": "com.nayan.myfirstproject"
        }
      },
      "oauth_client": [
        {
          "client_id": "278308056726-58q4jh2r76j5l1ikva5tr3josdl5tagc.apps.googleusercontent.com",
          "client_type": 1,
          "android_info": {
            "package_name": "com.nayan.myfirstproject",
            "certificate_hash": "5e8f16062ea3cd2c4a0d547876baa6f38cabf625"
          }
        },
        {
          "client_id": "278308056726-dogn8343dmdake4pfedaiet1t1f8a3l1.apps.googleusercontent.com",
          "client_type": 1,
          "android_info": {
            "package_name": "com.nayan.myfirstproject",
            "certificate_hash": "ccf7cb3110840bbdd7f3b924bd6c7f5c29f8f627"
          }
        },
        {
          "client_id": "278308056726-9ipfq96s6a869043cttl2h9mn2e2ihpk.apps.googleusercontent.com",
          "client_type": 3
        }
      ],
      "api_key": [
        {
          "current_key": "AIzaSyAUhzr4V6OhgRNbxHOSvhGgKSa45xOguQI"
        }
      ],
      "services": {
        "appinvite_service": {
          "other_platform_oauth_client": [
            {
              "client_id": "278308056726-9ipfq96s6a869043cttl2h9mn2e2ihpk.apps.googleusercontent.com",
              "client_type": 3
            }
          ]
        }
      }
    }
  ],
  "configuration_version": "1"
}